django_fakegen/__init__.py
django_fakegen/apps.py
django_fakegen/base.py
django_fakegen/registry.py
django_fakegen/generators/__init__.py
django_fakegen/generators/boolean.py
django_fakegen/generators/char.py
django_fakegen/generators/date.py
django_fakegen/generators/datetime.py
django_fakegen/generators/email.py
django_fakegen/generators/fk.py
django_fakegen/generators/float.py
django_fakegen/generators/int.py
django_fakegen/generators/m2m.py
django_fakegen/generators/o2o.py
django_fakegen/generators/text.py
django_fakegen/generators/time.py
django_fakegen/management/__init__.py
django_fakegen/management/commands/__init__.py
django_fakegen/management/commands/fakegen.py
django_fakegen-3.4.4.dist-info/METADATA
django_fakegen-3.4.4.dist-info/WHEEL
django_fakegen-3.4.4.dist-info/entry_points.txt
django_fakegen-3.4.4.dist-info/top_level.txt
django_fakegen-3.4.4.dist-info/RECORD
