Metadata-Version: 2.4
Name: django-fakegen
Version: 3.4.4
Summary: 🎭 Intelligent test data generation for Django applications with advanced field introspection
Home-page: https://github.com/your-username/django-fakegen
Author: Mezo
Author-email: motazfawzy73@gmail.com
Maintainer: Mezo
Maintainer-email: motazfawzy73@gmail.com
License: MIT
Project-URL: Homepage, https://github.com/Moataz0000/django_fakegen
Project-URL: Documentation, https://github.com/Moataz0000/django_fakegen
Project-URL: Source Code, https://github.com/Moataz0000/django_fakegen
Project-URL: Bug Reports, https://github.com/your-username/django-fakegen/issues
Keywords: django,faker,test-data,fixtures,mock-data,development,testing,database,seeding,generation,fake-data,sample-data,demo-data,populate
Platform: any
Classifier: Development Status :: 5 - Production/Stable
Classifier: Intended Audience :: Developers
Classifier: Intended Audience :: System Administrators
Classifier: Topic :: Software Development :: Libraries :: Python Modules
Classifier: Topic :: Software Development :: Testing
Classifier: Topic :: Database
Classifier: Topic :: Internet :: WWW/HTTP :: Dynamic Content
Classifier: Framework :: Django
Classifier: Framework :: Django :: 4.2
Classifier: Framework :: Django :: 5.0
Classifier: Framework :: Django :: 5.1
Classifier: License :: OSI Approved :: MIT License
Classifier: Programming Language :: Python
Classifier: Programming Language :: Python :: 3
Classifier: Programming Language :: Python :: 3.8
Classifier: Programming Language :: Python :: 3.9
Classifier: Programming Language :: Python :: 3.10
Classifier: Programming Language :: Python :: 3.11
Classifier: Programming Language :: Python :: 3.12
Classifier: Programming Language :: Python :: 3 :: Only
Classifier: Operating System :: OS Independent
Classifier: Operating System :: POSIX
Classifier: Operating System :: Microsoft :: Windows
Classifier: Operating System :: MacOS
Classifier: Environment :: Web Environment
Classifier: Environment :: Console
Requires-Python: >=3.8
Requires-Dist: Django<6.0,>=4.2
Requires-Dist: Faker>=20.0.0
Requires-Dist: python-dateutil>=2.8.0
Provides-Extra: dev
Requires-Dist: pytest>=7.0.0; extra == "dev"
Requires-Dist: pytest-django>=4.5.0; extra == "dev"
Requires-Dist: black>=22.0.0; extra == "dev"
Requires-Dist: flake8>=5.0.0; extra == "dev"
Requires-Dist: mypy>=1.0.0; extra == "dev"
Provides-Extra: performance
Requires-Dist: numpy>=1.21.0; extra == "performance"
Requires-Dist: pandas>=1.3.0; extra == "performance"
Provides-Extra: docs
Requires-Dist: sphinx>=5.0.0; extra == "docs"
Requires-Dist: sphinx-rtd-theme>=1.0.0; extra == "docs"
Dynamic: author
Dynamic: author-email
Dynamic: classifier
Dynamic: description
Dynamic: description-content-type
Dynamic: home-page
Dynamic: keywords
Dynamic: license
Dynamic: maintainer
Dynamic: maintainer-email
Dynamic: platform
Dynamic: project-url
Dynamic: provides-extra
Dynamic: requires-dist
Dynamic: requires-python
Dynamic: summary
